Metadata-Version: 2.1
Name: msvst
Version: 1.0
Summary: Multi-Scale Variance Stabilization Transform
Home-page: https://github.com/ruizca/msvst
Author: Angel Ruiz
Author-email: angel.ruizca@gmail.com
License: CeCILL
Classifier: Intended Audience :: Science/Research
Classifier: Topic :: Scientific/Engineering :: Astronomy
Classifier: Programming Language :: Python :: 3
Classifier: Operating System :: POSIX :: Linux
License-File: LICENSE.CeCILL
License-File: AUTHORS
